README.txt
setup.cfg
setup.py
csc/__init__.py
csc/conceptnet/__init__.py
csc/conceptnet/admin.py
csc/conceptnet/analogyspace.py
csc/conceptnet/analogyspace2.py
csc/conceptnet/models.py
csc/conceptnet/network.py
csc/conceptnet4/__init__.py
csc/concepttools/__init__.py
csc/corpus/__init__.py
csc/corpus/admin.py
csc/corpus/models.py
csc/corpus/views.py
csc/corpus/parse/__init__.py
csc/corpus/parse/admin.py
csc/corpus/parse/adverbs.py
csc/corpus/parse/build.py
csc/corpus/parse/models.py
csc/divisi2/__init__.py
csc/divisi2/blending.py
csc/divisi2/dataset.py
csc/divisi2/dense.py
csc/divisi2/examples.py
csc/divisi2/exceptions.py
csc/divisi2/export_svdview.py
csc/divisi2/fileIO.py
csc/divisi2/labels.py
csc/divisi2/network.py
csc/divisi2/operators.py
csc/divisi2/ordered_set.py
csc/divisi2/priodict.py
csc/divisi2/reconstructed.py
csc/divisi2/sparse.py
csc/divisi2/algorithms/__init__.py
csc/divisi2/algorithms/mds.py
csc/divisi2/algorithms/nmf.py
csc/divisi2/algorithms/svd.py
csc/django_settings/__init__.py
csc/lib/__init__.py
csc/lib/events/__init__.py
csc/lib/events/models.py
csc/lib/voting/__init__.py
csc/lib/voting/admin.py
csc/lib/voting/managers.py
csc/lib/voting/models.py
csc/lib/voting/views.py
csc/lib/voting/templatetags/__init__.py
csc/lib/voting/templatetags/voting_tags.py
csc/nl/__init__.py
csc/nl/euro.py
csc/nl/trie.py
csc/nl/ar/__init__.py
csc/nl/en/__init__.py
csc/nl/es/__init__.py
csc/nl/fi/__init__.py
csc/nl/fr/__init__.py
csc/nl/hu/__init__.py
csc/nl/it/__init__.py
csc/nl/ja/__init__.py
csc/nl/ja_cabocha/__init__.py
csc/nl/ja_cabocha/cabocha_token.py
csc/nl/ja_cabocha/chunk.py
csc/nl/ja_cabocha/debug.py
csc/nl/ja_cabocha/parser.py
csc/nl/ja_cabocha/properties.py
csc/nl/ja_cabocha/system.py
csc/nl/ja_cabocha/tree.py
csc/nl/ja_cabocha/util.py
csc/nl/ja_cabocha/utterance.py
csc/nl/ja_cabocha/word.py
csc/nl/ko/__init__.py
csc/nl/mblem/__init__.py
csc/nl/mblem/trie.py
csc/nl/nl/__init__.py
csc/nl/pt/__init__.py
csc/nl/zh/__init__.py
csc/pseudo_auth/__init__.py
csc_utils.egg-info/PKG-INFO
csc_utils.egg-info/SOURCES.txt
csc_utils.egg-info/dependency_links.txt
csc_utils.egg-info/namespace_packages.txt
csc_utils.egg-info/top_level.txt
