Metadata-Version: 1.1
Name: csc-utils
Version: 0.6.7
Summary: A set of utility functions for Python that the Commonsense Computing project uses in multiple projects.
Home-page: http://csc.media.mit.edu/
Author: MIT Media Lab, Software Agents group
Author-email: conceptnet@media.mit.edu
License: http://www.gnu.org/copyleft/gpl.html
Download-URL: http://divisi.media.mit.edu/dist/csc-util-0.6.7.tar.gz
Platform: any
Classifier: Intended Audience :: Developers
Classifier: Intended Audience :: Science/Research
Classifier: License :: OSI Approved :: GNU General Public License (GPL)
Classifier: Natural Language :: English
Classifier: Operating System :: MacOS
Classifier: Operating System :: Microsoft :: Windows
Classifier: Operating System :: POSIX
Classifier: Operating System :: Unix
Classifier: Programming Language :: C
Classifier: Programming Language :: Python :: 2.5
Classifier: Programming Language :: Python :: 2.6
Classifier: Topic :: Scientific/Engineering
Classifier: Topic :: Software Development
Classifier: Topic :: Text Processing :: Linguistic
